LICENSE
MANIFEST.in
requirements.txt
setup.cfg
setup.py
profiling/__about__.py
profiling/__init__.py
profiling/__main__.py
profiling/profiler.py
profiling/sortkeys.py
profiling/speedup.c
profiling/stats.py
profiling/utils.py
profiling/viewer.py
profiling.egg-info/PKG-INFO
profiling.egg-info/SOURCES.txt
profiling.egg-info/dependency_links.txt
profiling.egg-info/entry_points.txt
profiling.egg-info/requires.txt
profiling.egg-info/top_level.txt
profiling/remote/__init__.py
profiling/remote/asyncio.py
profiling/remote/background.py
profiling/remote/client.py
profiling/remote/gevent.py
profiling/remote/select.py
profiling/sampling/__init__.py
profiling/sampling/samplers.py
profiling/tracing/__init__.py
profiling/tracing/timers.py
test/requirements.txt
test/test_cli.py
test/test_profiler.py
test/test_sampling.py
test/test_stats.py
test/test_timers.py
test/test_tracing.py
test/test_utils.py
test/test_viewer.py